[
  {
    "name": "Dental Hygiene BS",
    "yearId": 1204,
    "classIds": [
      23746,
      23747,
      23748,
      23749,
      24001,
      23750,
      24535,
      23751
    ]
  },
  {
    "name": "Dental Hygiene Level 1",
    "yearId": 1204,
    "classIds": [
      23656,
      23657,
      23659,
      23669,
      23671,
      23674,
      23660,
      23662,
      23663,
      23665,
      23666,
      23667,
      23675,
      23676,
      23752,
      23678,
      23679,
      23682,
      23683,
      23684,
      23685,
      23686,
      23718,
      23719,
      23721,
      23722,
      23723,
      23725,
      23727,
      23728,
      23729,
      23730,
      23731
    ]
  },
  {
    "name": "Dental Hygiene Level 2",
    "yearId": 1204,
    "classIds": [
      23732,
      23733,
      23734,
      23736,
      23737,
      24543,
      23735,
      23738,
      23739,
      23740,
      23741,
      23742,
      23743,
      24080,
      24681,
      23744,
      24682,
      23745
    ]
  }
]